Metadata-Version: 1.1
Name: ricekey
Version: 1.0.1
Summary: OS-agnostic threaded keypress event detector for killing loops.
Home-page: https://github.com/ssriceboat/ricekey
Author: Kevin Sacca
Author-email: ssriceboat@gmail.com
License: MIT
Keywords: console terminal shell python key press keypress event
Platform: UNKNOWN
Classifier: Development Status :: 4 - Beta
Classifier: Intended Audience :: Developers
Classifier: Topic :: Software Development :: Build Tools
Classifier: License :: OSI Approved :: MIT License
Classifier: Programming Language :: Python :: 3
Classifier: Programming Language :: Python :: 3.5
Classifier: Programming Language :: Python :: 3.6
Classifier: Programming Language :: Python :: 3.7
